wallberry/__init__.py
wallberry/cache.py
wallberry/config.py
wallberry/db.py
wallberry/forecast.py
wallberry/graphs.py
wallberry/schema.sql
wallberry/sensors.py
wallberry/thermostat.py
wallberry/static/blank.png
wallberry/static/bootstrap-grid.min.css
wallberry/static/bootstrap-grid.min.css.map
wallberry/static/bootstrap-reboot.min.css
wallberry/static/bootstrap-reboot.min.css.map
wallberry/static/bootstrap.min.css
wallberry/static/bootstrap.min.css.map
wallberry/static/clear-day.png
wallberry/static/clear-night.png
wallberry/static/cloudy.png
wallberry/static/down-arrow.svg
wallberry/static/fog.png
wallberry/static/jquery.datetimepicker.full.min.js
wallberry/static/jquery.datetimepicker.min.css
wallberry/static/moment.min.js
wallberry/static/partly-cloudy-day.png
wallberry/static/partly-cloudy-night.png
wallberry/static/rain.png
wallberry/static/snow.png
wallberry/static/style.css
wallberry/static/sunrise.png
wallberry/static/sunset.png
wallberry/static/up-arrow.svg
wallberry/static/wind.png
wallberry/templates/alerts.html
wallberry/templates/currently.html
wallberry/templates/daily.html
wallberry/templates/history.html
wallberry/templates/hourly.html
wallberry/templates/index.html
wallberry/templates/log.html
wallberry/templates/sensors.html
wallberry/templates/thermostat.html
wallberry_uberpotato-1.3.1.dist-info/LICENSE
wallberry_uberpotato-1.3.1.dist-info/METADATA
wallberry_uberpotato-1.3.1.dist-info/WHEEL
wallberry_uberpotato-1.3.1.dist-info/top_level.txt
wallberry_uberpotato-1.3.1.dist-info/RECORD
