Metadata-Version: 2.1
Name: wallberry-uberpotato
Version: 1.3.1
Summary: Wall clock / weather forecast http server suitable for raspberry pi
Home-page: https://github.com/leoscholl/wallberry
Author: Leo Scholl
Author-email: leo.scholl@gmail.com
License: UNKNOWN
Platform: UNKNOWN
Requires-Dist: flask
Requires-Dist: python-forecastio
Requires-Dist: matplotlib
